jumeaux/__init__.py
jumeaux/executor.py
jumeaux/logger.py
jumeaux/main.py
jumeaux/models.py
jumeaux/utils.py
jumeaux/addons/__init__.py
jumeaux/addons/models.py
jumeaux/addons/parser.py
jumeaux/addons/did_challenge/__init__.py
jumeaux/addons/did_challenge/sleep.py
jumeaux/addons/did_challenge/tag.py
jumeaux/addons/dump/__init__.py
jumeaux/addons/dump/encoding.py
jumeaux/addons/dump/html.py
jumeaux/addons/dump/json.py
jumeaux/addons/dump/xml.py
jumeaux/addons/final/__init__.py
jumeaux/addons/final/csv.py
jumeaux/addons/final/json.py
jumeaux/addons/final/miroir.py
jumeaux/addons/final/notify.py
jumeaux/addons/final/summary.py
jumeaux/addons/final/viewer.py
jumeaux/addons/judgement/__init__.py
jumeaux/addons/judgement/ignore.py
jumeaux/addons/judgement/same.py
jumeaux/addons/log2reqs/__init__.py
jumeaux/addons/log2reqs/csv.py
jumeaux/addons/log2reqs/json.py
jumeaux/addons/log2reqs/plain.py
jumeaux/addons/log2reqs/yaml.py
jumeaux/addons/reqs2reqs/__init__.py
jumeaux/addons/reqs2reqs/add.py
jumeaux/addons/reqs2reqs/empty_guard.py
jumeaux/addons/reqs2reqs/filter.py
jumeaux/addons/reqs2reqs/head.py
jumeaux/addons/reqs2reqs/rename.py
jumeaux/addons/reqs2reqs/repeat.py
jumeaux/addons/reqs2reqs/replace.py
jumeaux/addons/reqs2reqs/shuffle.py
jumeaux/addons/res2dict/__init__.py
jumeaux/addons/res2dict/block.py
jumeaux/addons/res2dict/html.py
jumeaux/addons/res2dict/json.py
jumeaux/addons/res2dict/xml.py
jumeaux/addons/res2res/__init__.py
jumeaux/addons/res2res/json.py
jumeaux/addons/res2res/json_sort.py
jumeaux/addons/res2res/type.py
jumeaux/addons/store_criterion/__init__.py
jumeaux/addons/store_criterion/free.py
jumeaux/commands/__init__.py
jumeaux/commands/init/__init__.py
jumeaux/commands/init/main.py
jumeaux/commands/retry/__init__.py
jumeaux/commands/retry/main.py
jumeaux/commands/run/__init__.py
jumeaux/commands/run/main.py
jumeaux/commands/server/__init__.py
jumeaux/commands/server/main.py
jumeaux/commands/viewer/__init__.py
jumeaux/commands/viewer/main.py
jumeaux-6.0.1.dist-info/METADATA
jumeaux-6.0.1.dist-info/WHEEL
jumeaux-6.0.1.dist-info/entry_points.txt
jumeaux-6.0.1.dist-info/licenses/LICENSE
jumeaux-6.0.1.dist-info/RECORD
