Metadata-Version: 2.4
Name: jumeaux
Version: 6.0.1
Summary: Check difference between two responses of API.
Project-URL: homepage, https://tadashi-aikawa.github.io/jumeaux
Project-URL: repository, https://github.com/tadashi-aikawa/jumeaux/blob/master/README.md
Project-URL: documentation, https://tadashi-aikawa.github.io/jumeaux
Author-email: tadashi-aikawa <syou.maman@gmail.com>
License: MIT
License-File: LICENSE
Keywords: diff rest api response regression test
Classifier: Development Status :: 5 - Production/Stable
Classifier: Intended Audience :: Developers
Classifier: Topic :: Software Development :: Testing
Requires-Python: <4.0.0,>=3.9.0
Requires-Dist: beautifulsoup4<5.0.0,>=4.8.1
Requires-Dist: boto3<2.0.0,>=1.10.28
Requires-Dist: deepdiff==8.6.1
Requires-Dist: docopt<1.0.0,>=0.6.2
Requires-Dist: freezegun<2.0.0,>=1.5.1
Requires-Dist: jinja2<4.0.0,>=3.1.2
Requires-Dist: livereload<3.0.0,>=2.6.1
Requires-Dist: lxml<6.0.0,>=5.3.0
Requires-Dist: markupsafe==2.0.1
Requires-Dist: owcli<1.0.0,>=0.8.0
Requires-Dist: owlmixin<8.0.0,>=7.0.1
Requires-Dist: pydash<7.0.0,>=4.7.6
Requires-Dist: requests-toolbelt<1.0.0,>=0.9.1
Requires-Dist: requests<3.0.0,>=2.22.0
Requires-Dist: schema<1.0.0,>=0.7.1
Requires-Dist: tzlocal<3.0.0,>=2.0.0
Requires-Dist: urllib3<2
Requires-Dist: xmltodict<1.0.0,>=0.12.0
